autodonate_qiwi_api/__init__.py
autodonate_qiwi_api/main.py
autodonate_qiwi_api/migrations/0001_initial.py
autodonate_qiwi_api/migrations/__init__.py
autodonate_qiwi_api/models.py
autodonate_qiwi_api/types.py
autodonate_qiwi_api-0.1.5.dist-info/WHEEL
autodonate_qiwi_api-0.1.5.dist-info/METADATA
autodonate_qiwi_api-0.1.5.dist-info/RECORD
