Metadata-Version: 2.1
Name: autodonate-qiwi-api
Version: 0.1.5
Summary: QIWI API for Autodonate
Home-page: https://github.com/fire-squad/autodonate-qiwi-api
License: AGPL3
Author: firesquare
Author-email: team@firesquare.ru
Requires-Python: >=3.10,<4.0
Classifier: License :: Other/Proprietary License
Classifier: Programming Language :: Python :: 3
Classifier: Programming Language :: Python :: 3.10
Requires-Dist: Django (>=4.0.2,<5.0.0)
Requires-Dist: autodonate (>=0.1.0-alpha.0,<0.2.0)
Requires-Dist: requests (>=2.27.1,<3.0.0)
Project-URL: Repository, https://github.com/fire-squad/autodonate-qiwi-api
